axsemantics_sphinx_theme/__init__.py
axsemantics_sphinx_theme/breadcrumbs.html
axsemantics_sphinx_theme/layout.html
axsemantics_sphinx_theme/theme.conf
axsemantics_sphinx_theme/static/css/theme.css
axsemantics_sphinx_theme/static/fonts/fontawesome-webfont.eot
axsemantics_sphinx_theme/static/fonts/fontawesome-webfont.svg
axsemantics_sphinx_theme/static/fonts/fontawesome-webfont.ttf
axsemantics_sphinx_theme/static/fonts/fontawesome-webfont.woff
axsemantics_sphinx_theme/static/fonts/fontawesome-webfont.woff2
axsemantics_sphinx_theme-0.1.0.dist-info/LICENSE
axsemantics_sphinx_theme-0.1.0.dist-info/METADATA
axsemantics_sphinx_theme-0.1.0.dist-info/WHEEL
axsemantics_sphinx_theme-0.1.0.dist-info/entry_points.txt
axsemantics_sphinx_theme-0.1.0.dist-info/top_level.txt
axsemantics_sphinx_theme-0.1.0.dist-info/RECORD
