Metadata-Version: 2.1
Name: axsemantics-sphinx-theme
Version: 0.1.0
Summary: Sphinx theme used on AX Semantics internal documentation
Home-page: https://github.com/axsemantics/sphinx_theme/
Author: AX Semantics
Author-email: infrastructure@ax-semantics.com
License: MIT
Classifier: Framework :: Sphinx
Classifier: Framework :: Sphinx :: Theme
Classifier: Development Status :: 5 - Production/Stable
Classifier: License :: OSI Approved :: MIT License
Classifier: Environment :: Console
Classifier: Environment :: Web Environment
Classifier: Intended Audience :: Developers
Classifier: Programming Language :: Python :: 3
Classifier: Programming Language :: Python :: 3.9
Classifier: Programming Language :: Python :: 3.10
Classifier: Operating System :: OS Independent
Classifier: Topic :: Documentation
Classifier: Topic :: Software Development :: Documentation
Requires-Python: >=3.9
License-File: LICENSE
Requires-Dist: sphinx
